twdspring/__init__.py
twdspring/spring.py
twdspring-0.1.11.dist-info/licenses/LICENSE
twdspring-0.1.11.dist-info/METADATA
twdspring-0.1.11.dist-info/WHEEL
twdspring-0.1.11.dist-info/top_level.txt
twdspring-0.1.11.dist-info/RECORD
