Metadata-Version: 2.4
Name: twdspring
Version: 0.1.11
Summary: Stream Monitoring under the Time Warping Distance
Author-email: Aleksey Astafiev <aastafiev@gmail.com>
License: GPL-3.0-or-later
Project-URL: Homepage, https://aastafiev.github.io/twdspring/
Project-URL: Source, https://github.com/aastafiev/twdspring
Keywords: time warping distance,stream,online,dtw,pattern,search pattern,monitoring,stream monitoring,time series,time series analysis,distance
Classifier: Development Status :: 3 - Alpha
Classifier: Intended Audience :: Developers
Classifier: Intended Audience :: Science/Research
Classifier: Programming Language :: Python :: 3.12
Requires-Python: >=3.12
License-File: LICENSE
Requires-Dist: numpy
Provides-Extra: dev
Requires-Dist: pytest; extra == "dev"
Provides-Extra: docs
Requires-Dist: sphinx; extra == "docs"
Dynamic: license-file
